{
    "name": "OPD Claims — Approval Workflow",
    "nodes": [
        {
            "parameters": {
                "httpMethod": "GET",
                "path": "opd-approve",
                "responseMode": "responseNode",
                "options": {}
            },
            "id": "node_webhook_opd_approve",
            "name": "Webhook — Approval Click",
            "type": "n8n-nodes-base.webhook",
            "typeVersion": 2,
            "position": [240, 300],
            "webhookId": "opd-approve"
        },
        {
            "parameters": {
                "jsCode": "const query = $input.first().json.query || {};\n\nconst decision    = query.decision    || '';\nconst staffName   = decodeURIComponent(query.staffName   || '');\nconst submittedAt = decodeURIComponent(query.submittedAt || '');\n\nif (!['Approved', 'Rejected'].includes(decision)) {\n  throw new Error('Invalid decision. Must be Approved or Rejected.');\n}\nif (!staffName || !submittedAt) {\n  throw new Error('Missing staffName or submittedAt parameter.');\n}\n\nreturn [{\n  json: {\n    decision,\n    staffName,\n    submittedAt,\n    claimStatus: decision\n  }\n}];\n"
            },
            "id": "node_parse_opd_decision",
            "name": "Parse Approval Request",
            "type": "n8n-nodes-base.code",
            "typeVersion": 2,
            "position": [460, 300]
        },
        {
            "parameters": {
                "operation": "getRows",
                "documentId": {
                    "mode": "list",
                    "value": "1hhokFjoAiZlFTRf4KEmOmR4bReOwtbuzuEfzvrGUHqA"
                },
                "sheetName": {
                    "mode": "list",
                    "value": "Sheet1"
                },
                "options": {
                    "alwaysOutputData": true
                }
            },
            "id": "node_read_opd_row",
            "name": "Read Current Row",
            "type": "n8n-nodes-base.googleSheets",
            "typeVersion": 4.2,
            "position": [680, 300],
            "credentials": {
                "googleSheetsOAuth2Api": {
                    "id": "REPLACE_WITH_YOUR_CREDENTIAL_ID",
                    "name": "Google Sheets account 2"
                }
            }
        },
        {
            "parameters": {
                "jsCode": "// Read original request\nconst parsed = $('Parse Approval Request').first().json;\nconst targetTimestamp = parsed.submittedAt;\n\n// Search ALL rows to find the matching claim\nconst allRows = $input.all();\nconst matchedRow = allRows.find(item => item.json.submittedAt === targetTimestamp);\n\nif (!matchedRow) {\n  const html = `<!DOCTYPE html><html><head><meta charset=\"utf-8\"><title>Claim Not Found</title></head><body style=\"font-family:Arial,sans-serif;background:#f5f5f5;margin:0;padding:40px;min-height:100vh;display:flex;align-items:center;justify-content:center\"><div style=\"max-width:460px;background:white;border-radius:16px;padding:48px 36px;text-align:center;box-shadow:0 8px 32px rgba(0,0,0,0.1)\"><div style=\"font-size:72px;margin-bottom:16px\">\u2753</div><h1 style=\"color:#f59e0b;font-size:26px;margin:0 0 12px\">Claim Not Found</h1><p style=\"color:#555;font-size:15px\">We couldn't find this OPD claim in the database.</p></div></body></html>`;\n  return [{ json: { html, locked: true } }];\n}\n\nconst currentStatus = (matchedRow.json.claimStatus || '').trim();\n\nif (currentStatus === 'Approved' || currentStatus === 'Rejected') {\n  const emoji = currentStatus === 'Approved' ? '\u2705' : '\u274c';\n  const color = currentStatus === 'Approved' ? '#10b981' : '#ef4444';\n  const html = `<!DOCTYPE html><html><head><meta charset=\"utf-8\"><title>Already Processed</title></head><body style=\"font-family:Arial,sans-serif;background:#f5f5f5;margin:0;padding:40px;min-height:100vh;display:flex;align-items:center;justify-content:center;box-sizing:border-box\"><div style=\"max-width:460px;width:100%;background:white;border-radius:16px;padding:48px 36px;text-align:center;box-shadow:0 8px 32px rgba(0,0,0,0.1)\"><div style=\"font-size:72px;margin-bottom:16px\">\ud83d\udd12</div><h1 style=\"color:#6366f1;font-size:24px;margin:0 0 12px\">Already Processed</h1><p style=\"color:#555;font-size:15px;line-height:1.6;margin:0 0 24px\">This OPD claim has already been <strong>${currentStatus}</strong> ${emoji} and cannot be changed.</p><div style=\"background:#f3f4f6;border-radius:10px;padding:16px 20px;text-align:left\"><p style=\"margin:4px 0;font-size:13px;color:#444\">\ud83d\udc64 <strong>Staff:</strong> ${parsed.staffName}</p><p style=\"margin:4px 0;font-size:13px;color:${color}\">\ud83c\udff7 <strong>Final Status:</strong> ${currentStatus} ${emoji}</p></div><p style=\"margin-top:28px;color:#aaa;font-size:12px\">No further action is needed.</p></div></body></html>`;\n  return [{ json: { html, locked: true } }];\n}\n\n// Not decided — proceed\nreturn [{ json: { ...parsed, locked: false } }];"
            },
            "id": "node_check_lock_opd",
            "name": "Check If Already Decided",
            "type": "n8n-nodes-base.code",
            "typeVersion": 2,
            "position": [900, 300]
        },
        {
            "parameters": {
                "conditions": {
                    "options": {
                        "caseSensitive": false,
                        "leftValue": "",
                        "typeValidation": "strict"
                    },
                    "conditions": [
                        {
                            "id": "locked-check",
                            "leftValue": "={{ $json.locked }}",
                            "rightValue": false,
                            "operator": {
                                "type": "boolean",
                                "operation": "equals"
                            }
                        }
                    ],
                    "combinator": "and"
                },
                "options": {}
            },
            "id": "node_if_not_locked_opd",
            "name": "Is Not Yet Decided?",
            "type": "n8n-nodes-base.if",
            "typeVersion": 2,
            "position": [1120, 300]
        },
        {
            "parameters": {
                "operation": "update",
                "documentId": {
                    "mode": "list",
                    "value": "1hhokFjoAiZlFTRf4KEmOmR4bReOwtbuzuEfzvrGUHqA"
                },
                "sheetName": {
                    "mode": "list",
                    "value": "Sheet1"
                },
                "columns": {
                    "mappingMode": "defineBelow",
                    "matchingColumns": ["submittedAt"],
                    "value": {
                        "submittedAt": "={{ $json.submittedAt }}",
                        "claimStatus": "={{ $json.claimStatus }}"
                    },
                    "schema": [
                        {
                            "id": "submittedAt",
                            "displayName": "submittedAt",
                            "required": false,
                            "defaultMatch": true,
                            "canBeUsedToMatch": true,
                            "display": true,
                            "type": "string",
                            "readOnly": false,
                            "removed": false
                        },
                        {
                            "id": "claimStatus",
                            "displayName": "claimStatus",
                            "required": false,
                            "defaultMatch": false,
                            "canBeUsedToMatch": false,
                            "display": true,
                            "type": "string",
                            "readOnly": false,
                            "removed": false
                        }
                    ]
                },
                "options": {}
            },
            "id": "node_update_opd_status",
            "name": "Update Claim Status",
            "type": "n8n-nodes-base.googleSheets",
            "typeVersion": 4.2,
            "position": [1340, 200],
            "credentials": {
                "googleSheetsOAuth2Api": {
                    "id": "REPLACE_WITH_YOUR_CREDENTIAL_ID",
                    "name": "Google Sheets account 2"
                }
            }
        },
        {
            "parameters": {
                "jsCode": "// Re-read decision data from the earlier node (Sheets update wipes the fields)\nconst lockData  = $('Check If Already Decided').first().json;\nconst decision  = lockData.decision  || '';\nconst staffName = lockData.staffName || '';\nreturn [{ json: { decision, staffName, locked: false } }];\n"
            },
            "id": "node_prepare_response",
            "name": "Prepare Response",
            "type": "n8n-nodes-base.code",
            "typeVersion": 2,
            "position": [1560, 200]
        },
        {
            "parameters": {
                "jsCode": "const data      = $input.first().json;\nconst locked    = data.locked ?? false;\nconst decision  = data.decision  || '';\nconst staffName = data.staffName || '';\n\n// If locked (already processed), html is already built\nif (locked && data.html) {\n  return [{ json: { html: data.html } }];\n}\n\nconst isApproved = decision === 'Approved';\nconst emoji   = isApproved ? '✅' : '❌';\nconst color   = isApproved ? '#10b981' : '#ef4444';\nconst bgColor = isApproved ? '#ecfdf5'  : '#fef2f2';\nconst title   = isApproved ? 'OPD Claim Approved!' : 'OPD Claim Rejected';\nconst message = isApproved\n  ? `The OPD medical claim for <strong>${staffName}</strong> has been <strong>approved</strong> for reimbursement.`\n  : `The OPD medical claim for <strong>${staffName}</strong> has been <strong>rejected</strong>.`;\n\nconst html = `<!DOCTYPE html>\n<html><head><meta charset=\"utf-8\"><title>${title}</title></head>\n<body style=\"font-family:Arial,sans-serif;background:#f5f5f5;margin:0;padding:40px;min-height:100vh;display:flex;align-items:center;justify-content:center;box-sizing:border-box\">\n  <div style=\"max-width:460px;width:100%;background:white;border-radius:16px;padding:48px 36px;text-align:center;box-shadow:0 8px 32px rgba(0,0,0,0.1)\">\n    <div style=\"font-size:72px;margin-bottom:16px\">${emoji}</div>\n    <h1 style=\"color:${color};font-size:26px;margin:0 0 12px\">${title}</h1>\n    <p style=\"color:#555;font-size:15px;line-height:1.6;margin:0 0 24px\">${message}</p>\n    <div style=\"background:${bgColor};border:1px solid ${color}44;border-radius:10px;padding:16px 20px;text-align:left\">\n      <p style=\"margin:4px 0;font-size:13px;color:#444\">👤 <strong>Staff:</strong> ${staffName}</p>\n      <p style=\"margin:4px 0;font-size:13px;color:#444\">🏷 <strong>Decision:</strong> ${decision}</p>\n    </div>\n    <p style=\"margin-top:28px;color:#aaa;font-size:12px\">The OPD Claims Database has been updated automatically.</p>\n  </div>\n</body></html>`;\n\nreturn [{ json: { html } }];\n"
            },
            "id": "node_build_opd_page",
            "name": "Build Confirmation Page",
            "type": "n8n-nodes-base.code",
            "typeVersion": 2,
            "position": [1780, 300]
        },
        {
            "parameters": {
                "respondWith": "text",
                "responseBody": "={{ $json.html }}",
                "options": {
                    "responseCode": 200,
                    "responseHeaders": {
                        "entries": [
                            {
                                "name": "Content-Type",
                                "value": "text/html; charset=utf-8"
                            }
                        ]
                    }
                }
            },
            "id": "node_respond_opd_confirm",
            "name": "Respond — Confirmation Page",
            "type": "n8n-nodes-base.respondToWebhook",
            "typeVersion": 1,
            "position": [2000, 300]
        }
    ],
    "connections": {
        "Webhook — Approval Click":  { "main": [[{ "node": "Parse Approval Request",    "type": "main", "index": 0 }]] },
        "Parse Approval Request":    { "main": [[{ "node": "Read Current Row",           "type": "main", "index": 0 }]] },
        "Read Current Row":          { "main": [[{ "node": "Check If Already Decided",   "type": "main", "index": 0 }]] },
        "Check If Already Decided":  { "main": [[{ "node": "Is Not Yet Decided?",        "type": "main", "index": 0 }]] },
        "Is Not Yet Decided?": {
            "main": [
                [{ "node": "Update Claim Status",     "type": "main", "index": 0 }],
                [{ "node": "Build Confirmation Page", "type": "main", "index": 0 }]
            ]
        },
        "Update Claim Status":       { "main": [[{ "node": "Prepare Response",           "type": "main", "index": 0 }]] },
        "Prepare Response":          { "main": [[{ "node": "Build Confirmation Page",    "type": "main", "index": 0 }]] },
        "Build Confirmation Page":   { "main": [[{ "node": "Respond — Confirmation Page","type": "main", "index": 0 }]] }
    },
    "settings": {
        "executionOrder": "v1",
        "saveDataSuccessExecution": "all",
        "saveDataErrorExecution": "all"
    },
    "staticData": null,
    "tags": ["opd-claims"],
    "meta": {
        "instanceId": "opd-claims-approval-v4"
    }
}